teenageagi/__init__.py
teenageagi/core.py
teenageagi-0.1.0.dist-info/LICENSE
teenageagi-0.1.0.dist-info/METADATA
teenageagi-0.1.0.dist-info/WHEEL
teenageagi-0.1.0.dist-info/RECORD
