Metadata-Version: 2.1
Name: teenageagi
Version: 0.1.0
Summary: A Python package for teenage-agi
Home-page: https://github.com/jordan/teenage-agi
License: MIT
Keywords: ai,agi
Author: Jordan Plows 
Author-email: jordan@lightapi.com
Requires-Python: >=3.11,<4.0
Classifier: Development Status :: 4 - Beta
Classifier: Intended Audience :: Developers
Classifier: License :: OSI Approved :: MIT License
Classifier: Programming Language :: Python :: 3
Classifier: Programming Language :: Python :: 3.11
Classifier: Programming Language :: Python :: 3.12
Project-URL: Bug Tracker, https://github.com/jordan/teenage-agi/issues
Project-URL: Repository, https://github.com/jordan/teenage-agi
